opfgym/__init__.py
opfgym/constraints.py
opfgym/multi_stage.py
opfgym/objective.py
opfgym/opf_env.py
opfgym/reward.py
opfgym/security_constrained.py
opfgym/envs/__init__.py
opfgym/envs/eco_dispatch.py
opfgym/envs/load_shedding.py
opfgym/envs/max_renewable.py
opfgym/envs/q_market.py
opfgym/envs/voltage_control.py
opfgym/examples/__init__.py
opfgym/examples/custom_constraint.py
opfgym/examples/mixed_continuous_discrete.py
opfgym/examples/multi_stage.py
opfgym/examples/network_reconfiguration.py
opfgym/examples/non_simbench_net.py
opfgym/examples/partial_obs.py
opfgym/examples/pure_constraint_satisfaction.py
opfgym/examples/security_constrained.py
opfgym/examples/stochastic_obs.py
opfgym/simbench/__init__.py
opfgym/simbench/build_simbench_net.py
opfgym/simbench/data_split.py
opfgym/simbench/time_observation.py
opfgym/util/__init__.py
opfgym/util/import_class.py
opfgym/util/labeled_data.py
opfgym/wrappers/__init__.py
opfgym/wrappers/stochastic_obs.py
opfgym-1.0.1.dist-info/licenses/LICENSE
opfgym-1.0.1.dist-info/METADATA
opfgym-1.0.1.dist-info/WHEEL
opfgym-1.0.1.dist-info/top_level.txt
opfgym-1.0.1.dist-info/RECORD
