Metadata-Version: 2.4
Name: opfgym
Version: 1.0.1
Summary: Reinforcement Learning environments for learning the Optimal Power Flow
Author-email: Thomas Wolgast <thomas.wolgast@uni-oldenburg.de>
License: MIT License
Project-URL: Homepage, https://opf-gym.readthedocs.io
Project-URL: Repository, https://github.com/Digitalized-Energy-Systems/opfgym
Project-URL: Issues, https://github.com/Digitalized-Energy-Systems/opfgym/issues
Classifier: License :: OSI Approved :: MIT License
Classifier: Programming Language :: Python
Classifier: Programming Language :: Python :: 3
Classifier: Programming Language :: Python :: 3.10
Classifier: Programming Language :: Python :: 3.11
Classifier: Programming Language :: Python :: 3.12
Classifier: Programming Language :: Python :: 3.13
Classifier: Programming Language :: Python :: Implementation :: CPython
Classifier: Programming Language :: Python :: Implementation :: PyPy
Requires-Python: >=3.10
License-File: LICENSE
Requires-Dist: numpy>=1.22.4
Requires-Dist: scipy>=1.10.1
Requires-Dist: pandas>=1.3.5
Requires-Dist: matplotlib
Requires-Dist: lightsim2grid
Requires-Dist: pandapower<3.0,>=2.13.1
Requires-Dist: simbench>=1.4.0
Requires-Dist: gymnasium>=0.29.0
Provides-Extra: test
Requires-Dist: pytest; extra == "test"
Requires-Dist: pytest-cov; extra == "test"
Provides-Extra: docs
Requires-Dist: sphinx; extra == "docs"
Requires-Dist: furo; extra == "docs"
Dynamic: license-file
